{
	"configurations" : 
	[
		{
			"directories" : 
			[
				{
					"build" : ".",
					"jsonFile" : "directory-.-Debug-d0094a50bb2071803777.json",
					"minimumCMakeVersion" : 
					{
						"string" : "3.27.3"
					},
					"projectIndex" : 0,
					"source" : ".",
					"targetIndexes" : 
					[
						0
					]
				}
			],
			"name" : "Debug",
			"projects" : 
			[
				{
					"directoryIndexes" : 
					[
						0
					],
					"name" : "Template",
					"targetIndexes" : 
					[
						0
					]
				}
			],
			"targets" : 
			[
				{
					"directoryIndex" : 0,
					"id" : "Template::@6890427a1f51a3e7e1df",
					"jsonFile" : "target-Template-Debug-482a2552b07671cc40f3.json",
					"name" : "Template",
					"projectIndex" : 0
				}
			]
		}
	],
	"kind" : "codemodel",
	"paths" : 
	{
		"build" : "D:/TRABAJO/UMAKER/CURSOS/ARM - NUCLEO/STM32_FromScratch/NOVIEMBRE - 2023/Template/build/Debug",
		"source" : "D:/TRABAJO/UMAKER/CURSOS/ARM - NUCLEO/STM32_FromScratch/NOVIEMBRE - 2023/Template"
	},
	"version" : 
	{
		"major" : 2,
		"minor" : 6
	}
}
